rcvalid/__init__.py
rcvalid/rcvalid.py
rcvalid-0.0.1.dist-info/METADATA
rcvalid-0.0.1.dist-info/WHEEL
rcvalid-0.0.1.dist-info/top_level.txt
rcvalid-0.0.1.dist-info/RECORD
