Metadata-Version: 2.1
Name: rcvalid
Version: 0.0.1
Summary: Diferentes validaciones y formateos de inputs
Home-page: 
Author: Ranger Charro
